Metadata-Version: 1.0
Name: Ds-Statistics
Version: 0.2
Summary: Gaussian and Binomial distributions
Home-page: UNKNOWN
Author: ['Abhishek Ravi']
Author-email: abhishekravi60@gmail.com
License: UNKNOWN
Platform: UNKNOWN
